Workbook

Sheet Resumen
A1: Mes | B1: Compras | C1: Total ARS | D1: Total BTC | E1: Total Satoshis | F1: Precio prom. ARS/BTC
A2: Junio 2026 | B2: 29 | C2: ='Junio 2026'!B31 -> 18959.32 | D2: ='Junio 2026'!C31 -> 0.00019315 | E2: ='Junio 2026'!D31 -> 19315 | F2: =C2/D2 -> 98158530
A3: Julio 2026 | B3: 31 | C3: ='Julio 2026'!B33 -> 17005.82 | D3: ='Julio 2026'!C33 -> 0.00016807 | E3: ='Julio 2026'!D33 -> 16807 | F3: =C3/D3 -> 1.0118296e+08
A4: Agosto 2026 | B4: 31 | C4: ='Agosto 2026'!B33 -> 14365.33 | D4: ='Agosto 2026'!C33 -> 0.00013155 | E4: ='Agosto 2026'!D33 -> 13155 | F4: =C4/D4 -> 1.0920053e+08
A5: Septiembre 2026 | B5: 13 | C5: ='Septiembre 2026'!B15 -> 8704.2 | D5: ='Septiembre 2026'!C15 -> 6.859e-05 | E5: ='Septiembre 2026'!D15 -> 6859 | F5: =C5/D5 -> 1.2690188e+08
A6: TOTAL GENERAL | B6: =SUM(B2:B5) -> 104 | C6: =SUM(C2:C5) -> 59034.67 | D6: =SUM(D2:D5) -> 0.00056136 | E6: =SUM(E2:E5) -> 56136 | F6: =C6/D6 -> 1.0516366e+08
A8: Nota: DCA diario financiado con intereses de billeteras virtuales en ARS. Junio, julio y agosto cerrados. Septiembre en curso (incluye días sin compra como $0).

Sheet Junio 2026
A1: Fecha | B1: ARS invertidos | C1: BTC comprado | D1: Satoshis | E1: Precio ARS/BTC
A2: 1/6 | B2: 921.56 | C2: 8.48e-06 | D2: =C2*100000000 -> 848 | E2: =B2/C2 -> 1.0867453e+08
A3: 2/6 | B3: 288.8 | C3: 2.76e-06 | D3: =C3*100000000 -> 276 | E3: =B3/C3 -> 1.0463768e+08
A4: 3/6 | B4: 1325.83 | C4: 1.299e-05 | D4: =C4*100000000 -> 1299 | E4: =B4/C4 -> 1.0206543e+08
A5: 4/6 | B5: 1296.75 | C5: 1.327e-05 | D5: =C5*100000000 -> 1327 | E5: =B5/C5 -> 97720422
A6: 5/6 | B6: 1280.26 | C6: 1.326e-05 | D6: =C6*100000000 -> 1326 | E6: =B6/C6 -> 96550528
A7: 7/6 | B7: 74.44 | C7: 7.4e-07 | D7: =C7*100000000 -> 74 | E7: =B7/C7 -> 1.0059459e+08
A8: 8/6 | B8: 3061.47 | C8: 3.153e-05 | D8: =C8*100000000 -> 3153 | E8: =B8/C8 -> 97097050
A9: 9/6 | B9: 713.79 | C9: 7.32e-06 | D9: =C9*100000000 -> 732 | E9: =B9/C9 -> 97512295
A10: 10/6 | B10: 652.6 | C10: 6.95e-06 | D10: =C10*100000000 -> 695 | E10: =B10/C10 -> 93899281
A11: 11/6 | B11: 605.74 | C11: 6.26e-06 | D11: =C11*100000000 -> 626 | E11: =B11/C11 -> 96763578
A12: 12/6 | B12: 600.94 | C12: 6.19e-06 | D12: =C12*100000000 -> 619 | E12: =B12/C12 -> 97082391
A13: 13/6 | B13: 80.46 | C13: 8.3e-07 | D13: =C13*100000000 -> 83 | E13: =B13/C13 -> 96939759
... A30: 30/6 | B30: 282.99 | C30: 3e-06 | D30: =C30*100000000 -> 300 | E30: =B30/C30 -> 94330000
A31: TOTAL | B31: =SUM(B2:B30) -> 18959.32 | C31: =SUM(C2:C30) -> 0.00019315 | D31: =SUM(D2:D30) -> 19315 | E31: =B31/C31 -> 98158530
A32: PROMEDIO/día | B32: =AVERAGE(B2:B30) -> 653.76966 | C32: =AVERAGE(C2:C30) -> 6.6603448e-06 | D32: =AVERAGE(D2:D30) -> 666.03448

Sheet Julio 2026
A1: Fecha | B1: ARS invertidos | C1: BTC comprado | D1: Satoshis | E1: Precio ARS/BTC
A2: 1/7 | B2: 267.82 | C2: 2.87e-06 | D2: =C2*100000000 -> 287 | E2: =B2/C2 -> 93317073
A3: 2/7 | B3: 266.06 | C3: 2.77e-06 | D3: =C3*100000000 -> 277 | E3: =B3/C3 -> 96050542
A4: 3/7 | B4: 1229.15 | C4: 1.247e-05 | D4: =C4*100000000 -> 1247 | E4: =B4/C4 -> 98568565
A5: 4/7 | B5: 201.61 | C5: 2.02e-06 | D5: =C5*100000000 -> 202 | E5: =B5/C5 -> 99806931
A6: 5/7 | B6: 200.76 | C6: 2.01e-06 | D6: =C6*100000000 -> 201 | E6: =B6/C6 -> 99880597
A7: 6/7 | B7: 3123.11 | C7: 3.111e-05 | D7: =C7*100000000 -> 3111 | E7: =B7/C7 -> 1.0038926e+08
A8: 7/7 | B8: 943.34 | C8: 9.38e-06 | D8: =C8*100000000 -> 938 | E8: =B8/C8 -> 1.005693e+08
A9: 8/7 | B9: 938.49 | C9: 9.34e-06 | D9: =C9*100000000 -> 934 | E9: =B9/C9 -> 1.0048073e+08
A10: 9/7 | B10: 436.69 | C10: 4.37e-06 | D10: =C10*100000000 -> 437 | E10: =B10/C10 -> 99929062
A11: 10/7 | B11: 436.69 | C11: 4.25e-06 | D11: =C11*100000000 -> 425 | E11: =B11/C11 -> 1.0275059e+08
A12: 11/7 | B12: 436.69 | C12: 4.26e-06 | D12: =C12*100000000 -> 426 | E12: =B12/C12 -> 1.0250939e+08
A13: 12/7 | B13: 436.69 | C13: 4.28e-06 | D13: =C13*100000000 -> 428 | E13: =B13/C13 -> 1.0203037e+08
... A32: 31/7 | B32: 187.12 | C32: 1.83e-06 | D32: =C32*100000000 -> 183 | E32: =B32/C32 -> 1.0225137e+08
A33: TOTAL | B33: =SUM(B2:B32) -> 17005.82 | C33: =SUM(C2:C32) -> 0.00016807 | D33: =SUM(D2:D32) -> 16807 | E33: =B33/C33 -> 1.0118296e+08
A34: PROMEDIO/día | B34: =AVERAGE(B2:B32) -> 548.57484 | C34: =AVERAGE(C2:C32) -> 5.4216129e-06 | D34: =AVERAGE(D2:D32) -> 542.16129

Sheet Agosto 2026
A1: Fecha | B1: ARS invertidos | C1: BTC comprado | D1: Satoshis | E1: Precio ARS/BTC
A2: 1/8 | B2: 130.33 | C2: 1.29e-06 | D2: =C2*100000000 -> 129 | E2: =B2/C2 -> 1.0103101e+08
A3: 2/8 | B3: 130.33 | C3: 1.28e-06 | D3: =C3*100000000 -> 128 | E3: =B3/C3 -> 1.0182031e+08
A4: 3/8 | B4: 278.25 | C4: 2.72e-06 | D4: =C4*100000000 -> 272 | E4: =B4/C4 -> 1.0229779e+08
A5: 4/8 | B5: 1156.06 | C5: 1.127e-05 | D5: =C5*100000000 -> 1127 | E5: =B5/C5 -> 1.0257853e+08
A6: 5/8 | B6: 1114.35 | C6: 1.084e-05 | D6: =C6*100000000 -> 1084 | E6: =B6/C6 -> 1.0279982e+08
A7: 6/8 | B7: 1127.09 | C7: 1.083e-05 | D7: =C7*100000000 -> 1083 | E7: =B7/C7 -> 1.040711e+08
A8: 7/8 | B8: 957.06 | C8: 9.25e-06 | D8: =C8*100000000 -> 925 | E8: =B8/C8 -> 1.0346595e+08
A9: 8/8 | B9: 23.13 | C9: 2.2e-07 | D9: =C9*100000000 -> 22 | E9: =B9/C9 -> 1.0513636e+08
A10: 9/8 | B10: 96.1 | C10: 9.1e-07 | D10: =C10*100000000 -> 91 | E10: =B10/C10 -> 1.056044e+08
A11: 10/8 | B11: 1511.82 | C11: 1.443e-05 | D11: =C11*100000000 -> 1443 | E11: =B11/C11 -> 1.0476923e+08
A12: 11/8 | B12: 407.29 | C12: 3.97e-06 | D12: =C12*100000000 -> 397 | E12: =B12/C12 -> 1.0259194e+08
A13: 12/8 | B13: 406.61 | C13: 3.94e-06 | D13: =C13*100000000 -> 394 | E13: =B13/C13 -> 1.0320051e+08
... A32: 31/8 | B32: 835.9 | C32: 6.52e-06 | D32: =C32*100000000 -> 652 | E32: =B32/C32 -> 1.2820552e+08
A33: TOTAL | B33: =SUM(B2:B32) -> 14365.33 | C33: =SUM(C2:C32) -> 0.00013155 | D33: =SUM(D2:D32) -> 13155 | E33: =B33/C33 -> 1.0920053e+08
A34: PROMEDIO/día | B34: =AVERAGE(B2:B32) -> 463.39774 | C34: =AVERAGE(C2:C32) -> 4.2435484e-06 | D34: =AVERAGE(D2:D32) -> 424.35484

Sheet Septiembre 2026
A1: Fecha | B1: ARS invertidos | C1: BTC comprado | D1: Satoshis | E1: Precio ARS/BTC
A2: 1/9 | B2: 217.64 | C2: 1.74e-06 | D2: =C2*100000000 -> 174 | E2: =IFERROR(B2/C2,"") -> 1.2508046e+08
A3: 2/9 | B3: 214.14 | C3: 1.71e-06 | D3: =C3*100000000 -> 171 | E3: =IFERROR(B3/C3,"") -> 1.2522807e+08
A4: 3/9 | B4: 1484.69 | C4: 1.177e-05 | D4: =C4*100000000 -> 1177 | E4: =IFERROR(B4/C4,"") -> 1.2614189e+08
A5: 4/9 | B5: 0 | C5: 0 | D5: =C5*100000000 -> 0 | E5: =IFERROR(B5/C5,"")
A6: 5/9 | B6: 1337.63 | C6: 1.041e-05 | D6: =C6*100000000 -> 1041 | E6: =IFERROR(B6/C6,"") -> 1.2849472e+08
A7: 6/9 | B7: 0 | C7: 0 | D7: =C7*100000000 -> 0 | E7: =IFERROR(B7/C7,"")
A8: 7/9 | B8: 3193.12 | C8: 2.504e-05 | D8: =C8*100000000 -> 2504 | E8: =IFERROR(B8/C8,"") -> 1.2752077e+08
A9: 8/9 | B9: 701.54 | C9: 5.54e-06 | D9: =C9*100000000 -> 554 | E9: =IFERROR(B9/C9,"") -> 1.2663177e+08
A10: 9/9 | B10: 487.78 | C10: 3.85e-06 | D10: =C10*100000000 -> 385 | E10: =IFERROR(B10/C10,"") -> 1.266961e+08
A11: 10/9 | B11: 543.26 | C11: 4.35e-06 | D11: =C11*100000000 -> 435 | E11: =IFERROR(B11/C11,"") -> 1.2488736e+08
A12: 11/9 | B12: 484.49 | C12: 3.87e-06 | D12: =C12*100000000 -> 387 | E12: =IFERROR(B12/C12,"") -> 1.2519121e+08
A13: 12/9 | B13: 0 | C13: 0 | D13: =C13*100000000 -> 0 | E13: =IFERROR(B13/C13,"")
A14: 13/9 | B14: 39.91 | C14: 3.1e-07 | D14: =C14*100000000 -> 31 | E14: =IFERROR(B14/C14,"") -> 1.2874194e+08
A15: TOTAL | B15: =SUM(B2:B14) -> 8704.2 | C15: =SUM(C2:C14) -> 6.859e-05 | D15: =SUM(D2:D14) -> 6859 | E15: =B15/C15 -> 1.2690188e+08
A16: PROMEDIO/día | B16: =AVERAGE(B2:B14) -> 669.55385 | C16: =AVERAGE(C2:C14) -> 5.2761538e-06 | D16: =AVERAGE(D2:D14) -> 527.61538

Sheet Ganancia
A1: Análisis de Ganancia / Pérdida
A2: Precio de referencia: última compra cargada
A4: Total invertido (ARS) | B4: =Resumen!C6 -> 59034.67
A5: BTC acumulados | B5: =Resumen!D6 -> 0.00056136
A6: Satoshis acumulados | B6: =Resumen!E6 -> 56136
A7: Precio BTC de referencia (última compra) | B7: ='Septiembre 2026'!E14 -> 1.2874194e+08
A8: Valorización actual (ARS) | B8: =B5*B7 -> 72270.573
A9: Ganancia / Pérdida (ARS) | B9: =B8-B4 -> 13235.903
A10: Valorización de la inversión (%) | B10: =B9/B4*100 -> 22.420559
A12: Fecha de corte: última compra cargada en 'Septiembre 2026' (13/9).
A13: El precio de referencia es el implícito de la última operación de DCA, no una cotización de mercado externa.
